pyfem/__init__.py
pyfem/__main__.py
pyfem/amplitude/BaseAmplitude.py
pyfem/amplitude/TabularAmplitude.py
pyfem/amplitude/__init__.py
pyfem/amplitude/get_amplitude_data.py
pyfem/assembly/Assembly.py
pyfem/assembly/__init__.py
pyfem/bc/BaseBC.py
pyfem/bc/DirichletBC.py
pyfem/bc/NeumannBCConcentrated.py
pyfem/bc/NeumannBCDistributed.py
pyfem/bc/NeumannBCPressure.py
pyfem/bc/NeumannBCTraction.py
pyfem/bc/__init__.py
pyfem/bc/get_bc_data.py
pyfem/database/Database.py
pyfem/database/ODB.py
pyfem/database/__init__.py
pyfem/elements/BaseElement.py
pyfem/elements/CohesiveZone.py
pyfem/elements/Diffusion.py
pyfem/elements/SolidFiniteStrain.py
pyfem/elements/SolidGradientPhaseDamageSmallStrain.py
pyfem/elements/SolidPhaseDamageCZMSmallStrain.py
pyfem/elements/SolidPhaseDamageDiffusionSmallStrain.py
pyfem/elements/SolidPhaseDamageSmallStrain.py
pyfem/elements/SolidSmallStrain.py
pyfem/elements/SolidThermalSmallStrain.py
pyfem/elements/SurfaceEffect.py
pyfem/elements/Thermal.py
pyfem/elements/__init__.py
pyfem/elements/get_element_data.py
pyfem/elements/set_element_field_variables.py
pyfem/fem/Timer.py
pyfem/fem/__init__.py
pyfem/fem/constants.py
pyfem/io/Amplitude.py
pyfem/io/BC.py
pyfem/io/BaseIO.py
pyfem/io/Dof.py
pyfem/io/Material.py
pyfem/io/Mesh.py
pyfem/io/Output.py
pyfem/io/Parameter.py
pyfem/io/Properties.py
pyfem/io/Section.py
pyfem/io/Solver.py
pyfem/io/__init__.py
pyfem/io/arguments.py
pyfem/io/write_vtk.py
pyfem/isoelements/IsoElementDiagram.py
pyfem/isoelements/IsoElementShape.py
pyfem/isoelements/__init__.py
pyfem/isoelements/get_iso_element_type.py
pyfem/isoelements/shape_functions.py
pyfem/job/Job.py
pyfem/job/ParallelJob.py
pyfem/job/__init__.py
pyfem/materials/BaseMaterial.py
pyfem/materials/Cohesive.py
pyfem/materials/DiffusionIsotropic.py
pyfem/materials/ElasticIsotropic.py
pyfem/materials/GradientPhaseFieldDamage.py
pyfem/materials/MechanicalThermalExpansion.py
pyfem/materials/PhaseFieldDamage.py
pyfem/materials/PhaseFieldDamageCZM.py
pyfem-0.3.7.1.dist-info/LICENSE
pyfem-0.3.7.1.dist-info/METADATA
pyfem-0.3.7.1.dist-info/WHEEL
pyfem-0.3.7.1.dist-info/entry_points.txt
pyfem-0.3.7.1.dist-info/top_level.txt
pyfem-0.3.7.1.dist-info/RECORD
