Metadata-Version: 2.1
Name: pyfem
Version: 0.3.7.1
Summary: Python Finite Element Method
Home-page: https://github.com/sunwhale/pyfem
Author: Jingyu Sun
Author-email: sun.jingyu@outlook.com
Project-URL: Bug Tracker, https://github.com/sunwhale/pyfem/issues
Classifier: Programming Language :: Python :: 3
Classifier: License :: OSI Approved :: Apache Software License
Classifier: Operating System :: OS Independent
Requires-Python: >=3.9
License-File: LICENSE
Requires-Dist: numpy
Requires-Dist: scipy
Requires-Dist: meshio
Requires-Dist: tomli
Requires-Dist: colorlog
Requires-Dist: sympy
Requires-Dist: tomli-w
Requires-Dist: h5py
